pythonanywhere_client/__init__.py
pythonanywhere_client-1.1.6.dist-info/LICENSE
pythonanywhere_client-1.1.6.dist-info/METADATA
pythonanywhere_client-1.1.6.dist-info/WHEEL
pythonanywhere_client-1.1.6.dist-info/top_level.txt
pythonanywhere_client-1.1.6.dist-info/RECORD
