Metadata-Version: 2.1
Name: pythonanywhere-client
Version: 1.1.6
Summary: This is a Python library for interacting with the PythonAnywhere platform
Author-email: sysproxy <sysproxy64@gmail.com>
Classifier: Intended Audience :: Developers
Classifier: Operating System :: OS Independent
Classifier: Programming Language :: Python :: 3
Classifier: Topic :: Internet :: WWW/HTTP
Classifier: Topic :: Software Development :: Libraries :: Python Modules
Requires-Python: >=3.10
License-File: LICENSE
Requires-Dist: requests >=2.28.2
Requires-Dist: selenium >=4.12.0
Provides-Extra: test
Requires-Dist: flake8 >=6.0.0 ; extra == 'test'
Requires-Dist: pytest >=7.2.2 ; extra == 'test'
